medpret/__init__.py
medpret-0.0.0.dist-info/METADATA
medpret-0.0.0.dist-info/WHEEL
medpret-0.0.0.dist-info/top_level.txt
medpret-0.0.0.dist-info/RECORD
