Metadata-Version: 2.1
Name: medpret
Version: 0.0.0
Summary: Coming Soon
Home-page: https://url.com
Download-URL: https://download_url.com
Author: Development Team
Author-email: test@test.com
License: MIT
Project-URL: Source, https://github.com/source
Keywords: python3 python medpret
Classifier: Development Status :: 1 - Planning
Classifier: Programming Language :: Python :: 3.6
Classifier: Programming Language :: Python :: 3.7
Classifier: Programming Language :: Python :: 3.8
Classifier: Programming Language :: Python :: 3.9
Classifier: Programming Language :: Python :: 3.10
Classifier: Programming Language :: Python :: 3.11
Classifier: Programming Language :: Python :: 3.12
Requires-Python: >=3.6
